pygbm/__init__.py
pygbm/cli.py
pygbm/gbm_simulator.py
pygbm_liz-0.1.0.dist-info/METADATA
pygbm_liz-0.1.0.dist-info/WHEEL
pygbm_liz-0.1.0.dist-info/entry_points.txt
pygbm_liz-0.1.0.dist-info/top_level.txt
pygbm_liz-0.1.0.dist-info/RECORD
