Metadata-Version: 2.1
Name: pygbm_liz
Version: 0.1.0
Summary: A package to simulate Geometric Brownian Motion
Author-email: Liz Tan <eszt2@cam.ac.uk>
License: MIT
Keywords: geometric brownian motion,stochastic processes,finance,simulation
Requires-Python: >=3.6
Requires-Dist: numpy>=1.18.0
Requires-Dist: matplotlib>=3.0.0
